localhook/__init__.py
localhook/hook.py
localhook-0.0.3.dist-info/LICENSE
localhook-0.0.3.dist-info/METADATA
localhook-0.0.3.dist-info/WHEEL
localhook-0.0.3.dist-info/entry_points.txt
localhook-0.0.3.dist-info/top_level.txt
localhook-0.0.3.dist-info/RECORD
