Metadata-Version: 2.1
Name: localhook
Version: 0.0.3
Summary: Receive webhooks to your Terminal
Home-page: https://github.com/kekayan/localhook
Author: Kekayan Nanthakumar
Author-email: kekayan.nanthakumar@gmail.com
License: UNKNOWN
Platform: UNKNOWN
Requires-Dist: pyngrok (>=5.0.2)
Requires-Dist: Flask (==2.0.1)
Requires-Dist: PyYAML (>=5.3.1)
Requires-Dist: rich
Requires-Dist: waitress
Requires-Dist: click (==8.0.1)
